LICENSE.txt
MANIFEST.in
README.rst
setup.cfg
setup.py
data/rin-ucs.yml.example
rin_driver_ucs.egg-info/PKG-INFO
rin_driver_ucs.egg-info/SOURCES.txt
rin_driver_ucs.egg-info/dependency_links.txt
rin_driver_ucs.egg-info/entry_points.txt
rin_driver_ucs.egg-info/requires.txt
rin_driver_ucs.egg-info/top_level.txt
rin_ucs/__init__.py
rin_ucs/list_servers.py