Metadata-Version: 1.1
Name: rin-driver-ucs
Version: 0.0.12
Summary: A command line utilities to operate UCS manager.
Home-page: UNKNOWN
Author: Hiroyasu OHYAMA
Author-email: oyama-hiroyasu@dmm.com
License: MIT
Platform: UNKNOWN
Classifier: License :: OSI Approved :: MIT License
Classifier: Programming Language :: Python :: 2
Classifier: Programming Language :: Python :: 2.6
Classifier: Programming Language :: Python :: 2.7
Classifier: Programming Language :: Python :: 3
Classifier: Programming Language :: Python :: 3.3
Classifier: Programming Language :: Python :: 3.4
Classifier: Programming Language :: Python :: 3.5
